divide/__init__.py
divide/divide_by_three.py
multiply/__init__.py
multiply/multiply_by_three.py
Kartikpkg-2.0.dist-info/LICENSE.txt
Kartikpkg-2.0.dist-info/METADATA
Kartikpkg-2.0.dist-info/WHEEL
Kartikpkg-2.0.dist-info/top_level.txt
Kartikpkg-2.0.dist-info/RECORD
