Metadata-Version: 2.1
Name: Kartikpkg
Version: 2.0
Summary: A simple Python package by Kartik Soni
Author: Kartik
Author-email: kartik22soni@gmail.com
Classifier: Programming Language :: Python :: 3
Classifier: License :: OSI Approved :: MIT License
Classifier: Operating System :: OS Independent
Requires-Python: >=3.6
License-File: LICENSE.txt
